flaxspeaker/__init__.py
flaxspeaker/__main__.py
flaxspeaker/dataset.py
flaxspeaker/evaluation.py
flaxspeaker/feature_extraction.py
flaxspeaker/generate_csv.py
flaxspeaker/neural_net.py
flaxspeaker/specaug.py
flaxspeaker-0.0.2.dist-info/LICENSE
flaxspeaker-0.0.2.dist-info/METADATA
flaxspeaker-0.0.2.dist-info/WHEEL
flaxspeaker-0.0.2.dist-info/top_level.txt
flaxspeaker-0.0.2.dist-info/RECORD
