Metadata-Version: 2.1
Name: flaxspeaker
Version: 0.0.2
Summary: A simple speaker recognition library in JAX and Flax.
Home-page: https://github.com/wq2012/FlaxSpeaker
Author: Quan Wang
Author-email: quanw@google.com
License: UNKNOWN
Platform: UNKNOWN
Classifier: Programming Language :: Python :: 3
Classifier: License :: OSI Approved :: Apache Software License
Classifier: Operating System :: OS Independent
License-File: LICENSE
